src/__init__.py
src/cli/__init__.py
src/cli/available.py
src/cli/cliRunner.py
src/cli/create.py
src/cli/exceptions.py
src/cli/jsonReader.py
src/cli/list.py
src/cli/parser.py
src/cli/results.py
src/cli/show.py
src/cli/utils.py
tests/__init__.py
tests/test_helpers.py
tests/integration/__init__.py
tests/system/__init__.py
tests/system/test_analysis.py
tests/system/test_available.py
tests/system/test_change_name.py
tests/system/test_help.py
tests/system/test_import.py
tests/system/test_list.py
tests/system/test_no_env.py
tests/system/test_show.py
tests/system/test_sigint.py
tests/unit/__init__.py
tests/unit/test_available.py
tests/unit/test_change_name.py
tests/unit/test_create.py
tests/unit/test_jsonReader.py
tests/unit/test_list.py
tests/unit/test_results.py
tests/unit/test_show.py
measuresoftgram3-3.0.0.dist-info/LICENSE
measuresoftgram3-3.0.0.dist-info/METADATA
measuresoftgram3-3.0.0.dist-info/WHEEL
measuresoftgram3-3.0.0.dist-info/entry_points.txt
measuresoftgram3-3.0.0.dist-info/top_level.txt
measuresoftgram3-3.0.0.dist-info/RECORD
