Metadata-Version: 2.1
Name: measuresoftgram3
Version: 3.0.0
License-File: LICENSE
Requires-Dist: inquirer (==2.8.0)
Requires-Dist: requests
Requires-Dist: pytz
Requires-Dist: tabulate (==0.8.10)
Requires-Dist: termcolor (==1.1.0)
Provides-Extra: dev
Requires-Dist: pytest ; extra == 'dev'
Requires-Dist: pytest-cov ; extra == 'dev'
Requires-Dist: setuptools ; extra == 'dev'
Requires-Dist: wheel ; extra == 'dev'
